odoo/addons/l10n_ro_stock_account_date_wizard/README.rst
odoo/addons/l10n_ro_stock_account_date_wizard/__init__.py
odoo/addons/l10n_ro_stock_account_date_wizard/__manifest__.py
odoo/addons/l10n_ro_stock_account_date_wizard/i18n/l10n_ro_stock_account_date_wizard.pot
odoo/addons/l10n_ro_stock_account_date_wizard/i18n/ro.po
odoo/addons/l10n_ro_stock_account_date_wizard/readme/CONTRIBUTORS.rst
odoo/addons/l10n_ro_stock_account_date_wizard/readme/DESCRIPTION.rst
odoo/addons/l10n_ro_stock_account_date_wizard/readme/INSTALL.rst
odoo/addons/l10n_ro_stock_account_date_wizard/static/description/icon.png
odoo/addons/l10n_ro_stock_account_date_wizard/static/description/index.html
odoo/addons/l10n_ro_stock_account_date_wizard/static/src/css/report.css
odoo/addons/l10n_ro_stock_account_date_wizard/tests/__init__.py
odoo/addons/l10n_ro_stock_account_date_wizard/tests/test_stock_accounting_date.py
odoo/addons/l10n_ro_stock_account_date_wizard/wizard/__init__.py
odoo/addons/l10n_ro_stock_account_date_wizard/wizard/stock_backorder_confirmation.py
odoo/addons/l10n_ro_stock_account_date_wizard/wizard/stock_backorder_confirmation_views.xml
odoo/addons/l10n_ro_stock_account_date_wizard/wizard/stock_immediate_transfer.py
odoo/addons/l10n_ro_stock_account_date_wizard/wizard/stock_immediate_transfer_views.xml
odoo14_addon_l10n_ro_stock_account_date_wizard-14.0.3.3.0.dist-info/METADATA
odoo14_addon_l10n_ro_stock_account_date_wizard-14.0.3.3.0.dist-info/WHEEL
odoo14_addon_l10n_ro_stock_account_date_wizard-14.0.3.3.0.dist-info/top_level.txt
odoo14_addon_l10n_ro_stock_account_date_wizard-14.0.3.3.0.dist-info/RECORD
